fs_base/__init__.py
fs_base/app_ini_util.py
fs_base/app_mini.py
fs_base/app_tray_menu.py
fs_base/base_menu_bar.py
fs_base/base_util.py
fs_base/config_manager.py
fs_base/const/__init__.py
fs_base/const/app_constants.py
fs_base/message_util.py
fs_base/resources/fonts/AlimamaFangYuanTiVF-Thin.ttf
fs_base/resources/qss/base.qss
fs_base/widget/__init__.py
fs_base/widget/custom_progress_widget.py
fs_base/widget/hover_image_button.py
fs_base/widget/image_button.py
fs_base/widget/menu_window_widget.py
fs_base/widget/tab_animation_widget.py
fs_base/widget/toolbox_animation_widget.py
fs_base/widget/transparent_textbox_widget.py
fs_base-0.1.2.dist-info/LICENSE
fs_base-0.1.2.dist-info/METADATA
fs_base-0.1.2.dist-info/WHEEL
fs_base-0.1.2.dist-info/RECORD
