Metadata-Version: 2.3
Name: fs_base
Version: 0.1.2
Summary: 一个基础库，基于 PySide6 构建，代码由ChatGPT、DeepSeek提供参考，本人只是搬运工。
License: Apache License
Author: flowstone
Author-email: xueyao.me@gmail.com
Requires-Python: >=3.6
Classifier: Programming Language :: Python :: 3
Classifier: Operating System :: OS Independent
Requires-Dist: PySide6
Requires-Dist: loguru
Project-URL: Homepage, https://github.com/flowstone/fs_base
